[
  {
    "full_name": "rohitrastogi/Interview-Prep",
    "stargazers_count": 11,
    "open_issues_count": 0,
    "forks_count": 0
  },
  {
    "full_name": "phuocng/frontend-tips",
    "stargazers_count": 603,
    "open_issues_count": 0,
    "forks_count": 54
  },
  {
    "full_name": "alienkitty/space.js",
    "stargazers_count": 240,
    "open_issues_count": 0,
    "forks_count": 6
  },
  {
    "full_name": "nick-keller/react-datasheet-grid",
    "stargazers_count": 1588,
    "open_issues_count": 43,
    "forks_count": 130
  },
  {
    "full_name": "microsoft/vscode-extension-samples",
    "stargazers_count": 7786,
    "open_issues_count": 73,
    "forks_count": 3254
  },
  {
    "full_name": "pactumjs/pactum",
    "stargazers_count": 475,
    "open_issues_count": 14,
    "forks_count": 44
  },
  {
    "full_name": "CanadaHonk/test262.fyi",
    "stargazers_count": 25,
    "open_issues_count": 16,
    "forks_count": 4
  },
  {
    "full_name": "bitjson/qr-code",
    "stargazers_count": 770,
    "open_issues_count": 7,
    "forks_count": 36
  },
  {
    "full_name": "Arif-un/react-mix-tag-input",
    "stargazers_count": 1,
    "open_issues_count": 5,
    "forks_count": 0
  },
  {
    "full_name": "webstudio-is/webstudio",
    "stargazers_count": 3347,
    "open_issues_count": 203,
    "forks_count": 312
  },
  {
    "full_name": "adbayb/termost",
    "stargazers_count": 134,
    "open_issues_count": 1,
    "forks_count": 1
  },
  {
    "full_name": "josdejong/csv42",
    "stargazers_count": 98,
    "open_issues_count": 0,
    "forks_count": 6
  },
  {
    "full_name": "isaacs/node-glob",
    "stargazers_count": 8252,
    "open_issues_count": 5,
    "forks_count": 528
  },
  {
    "full_name": "customerio/howtotarget",
    "stargazers_count": 39,
    "open_issues_count": 5,
    "forks_count": 9
  },
  {
    "full_name": "replicate/zoo",
    "stargazers_count": 285,
    "open_issues_count": 16,
    "forks_count": 74
  },
  {
    "full_name": "vanjs-org/van",
    "stargazers_count": 3197,
    "open_issues_count": 26,
    "forks_count": 77
  },
  {
    "full_name": "redwoodjs/redwood",
    "stargazers_count": 16602,
    "open_issues_count": 433,
    "forks_count": 958
  },
  {
    "full_name": "PlasmoHQ/plasmo",
    "stargazers_count": 7624,
    "open_issues_count": 152,
    "forks_count": 255
  },
  {
    "full_name": "sindresorhus/devtools-detect",
    "stargazers_count": 1962,
    "open_issues_count": 23,
    "forks_count": 218
  },
  {
    "full_name": "nuxt/devtools",
    "stargazers_count": 2524,
    "open_issues_count": 45,
    "forks_count": 128
  },
  {
    "full_name": "chibat/chrome-extension-typescript-starter",
    "stargazers_count": 2180,
    "open_issues_count": 7,
    "forks_count": 371
  },
  {
    "full_name": "Arif-un/react-multiple-select-dropdown-lite",
    "stargazers_count": 10,
    "open_issues_count": 15,
    "forks_count": 6
  },
  {
    "full_name": "gustavoguichard/string-ts",
    "stargazers_count": 1096,
    "open_issues_count": 6,
    "forks_count": 17
  },
  {
    "full_name": "mnquintana/awesome-whiteboardless-interviews",
    "stargazers_count": 28,
    "open_issues_count": 0,
    "forks_count": 7
  },
  {
    "full_name": "measuredco/puck",
    "stargazers_count": 3947,
    "open_issues_count": 55,
    "forks_count": 158
  },
  {
    "full_name": "Arif-un/jcof-php",
    "stargazers_count": 1,
    "open_issues_count": 0,
    "forks_count": 2
  },
  {
    "full_name": "mortie/jcof",
    "stargazers_count": 152,
    "open_issues_count": 7,
    "forks_count": 1
  },
  {
    "full_name": "mdx-editor/editor",
    "stargazers_count": 949,
    "open_issues_count": 29,
    "forks_count": 71
  },
  {
    "full_name": "alnahian2003/learn-laravel",
    "stargazers_count": 91,
    "open_issues_count": 0,
    "forks_count": 55
  },
  {
    "full_name": "guocaoyi/create-chrome-ext",
    "stargazers_count": 945,
    "open_issues_count": 11,
    "forks_count": 69
  }
]