[
  {
    "full_name": "loverajoel/jstips",
    "stargazers_count": 12259,
    "open_issues_count": 9,
    "forks_count": 805
  },
  {
    "full_name": "elsewhencode/project-guidelines",
    "stargazers_count": 27266,
    "open_issues_count": 12,
    "forks_count": 3072
  },
  {
    "full_name": "goldbergyoni/javascript-testing-best-practices",
    "stargazers_count": 18935,
    "open_issues_count": 53,
    "forks_count": 1679
  },
  {
    "full_name": "Developer-Y/Scalable-Software-Architecture",
    "stargazers_count": 1474,
    "open_issues_count": 0,
    "forks_count": 355
  },
  {
    "full_name": "BuilderIO/framework-benchmarks",
    "stargazers_count": 301,
    "open_issues_count": 4,
    "forks_count": 13
  },
  {
    "full_name": "jhuangtw/xg2xg",
    "stargazers_count": 11617,
    "open_issues_count": 36,
    "forks_count": 857
  },
  {
    "full_name": "brillout/awesome-react-components",
    "stargazers_count": 32137,
    "open_issues_count": 2,
    "forks_count": 2774
  },
  {
    "full_name": "codecrafters-io/build-your-own-x",
    "stargazers_count": 163939,
    "open_issues_count": 268,
    "forks_count": 15353
  },
  {
    "full_name": "alan2207/bulletproof-react",
    "stargazers_count": 13963,
    "open_issues_count": 22,
    "forks_count": 1107
  },
  {
    "full_name": "bregman-arie/devops-exercises",
    "stargazers_count": 29201,
    "open_issues_count": 12,
    "forks_count": 6248
  },
  {
    "full_name": "nodejs/corepack",
    "stargazers_count": 1025,
    "open_issues_count": 20,
    "forks_count": 61
  },
  {
    "full_name": "sourabh-joshi/awesome-quincy-larson-emails",
    "stargazers_count": 902,
    "open_issues_count": 0,
    "forks_count": 117
  },
  {
    "full_name": "anderspitman/awesome-tunneling",
    "stargazers_count": 6122,
    "open_issues_count": 36,
    "forks_count": 268
  },
  {
    "full_name": "stefanjudis/tiny-helpers",
    "stargazers_count": 792,
    "open_issues_count": 16,
    "forks_count": 274
  },
  {
    "full_name": "twitter/typeahead.js",
    "stargazers_count": 16433,
    "open_issues_count": 511,
    "forks_count": 3277
  },
  {
    "full_name": "robinweser/fela",
    "stargazers_count": 2185,
    "open_issues_count": 10,
    "forks_count": 198
  },
  {
    "full_name": "TencentARC/GFPGAN",
    "stargazers_count": 21891,
    "open_issues_count": 152,
    "forks_count": 3249
  },
  {
    "full_name": "andrew--r/frontend-case-studies",
    "stargazers_count": 6734,
    "open_issues_count": 27,
    "forks_count": 389
  },
  {
    "full_name": "WebDevsCom/webDevsCom",
    "stargazers_count": 623,
    "open_issues_count": 8,
    "forks_count": 75
  },
  {
    "full_name": "ossu/computer-science",
    "stargazers_count": 123180,
    "open_issues_count": 9,
    "forks_count": 16424
  },
  {
    "full_name": "GoulartNogueira/BadUI",
    "stargazers_count": 290,
    "open_issues_count": 2,
    "forks_count": 8
  },
  {
    "full_name": "lahmatiy/react-render-tracker",
    "stargazers_count": 1826,
    "open_issues_count": 11,
    "forks_count": 26
  },
  {
    "full_name": "open-source-projects-contributes/problem-tutorials",
    "stargazers_count": 1,
    "open_issues_count": 0,
    "forks_count": 0
  },
  {
    "full_name": "frejs/fre",
    "stargazers_count": 3474,
    "open_issues_count": 18,
    "forks_count": 334
  },
  {
    "full_name": "randallkanna/awesome-job-list",
    "stargazers_count": 1217,
    "open_issues_count": 2,
    "forks_count": 133
  },
  {
    "full_name": "know-prashant/awesome-algorithms",
    "stargazers_count": 2,
    "open_issues_count": 0,
    "forks_count": 0
  },
  {
    "full_name": "know-prashant/Best-websites-a-programmer-should-visit",
    "stargazers_count": 1,
    "open_issues_count": 0,
    "forks_count": 1
  },
  {
    "full_name": "gztchan/awesome-design",
    "stargazers_count": 13937,
    "open_issues_count": 28,
    "forks_count": 1146
  },
  {
    "full_name": "Shafin098/pakhi-bhasha",
    "stargazers_count": 114,
    "open_issues_count": 0,
    "forks_count": 0
  },
  {
    "full_name": "nhn/tui.editor",
    "stargazers_count": 15112,
    "open_issues_count": 388,
    "forks_count": 1499
  }
]